Pgraph/Pgraph.py
Pgraph/__init__.py
Pgraph/studio_file.pgsx
Pgraph/solver/__init__.py
Pgraph/solver/input.in
Pgraph/solver/libgcc_s_dw2-1.dll
Pgraph/solver/libgcc_s_seh-1.dll
Pgraph/solver/libgomp-1.dll
Pgraph/solver/libstdc++-6.dll
Pgraph/solver/libwinpthread-1.dll
Pgraph/solver/pgraph_solver.exe
Pgraph/solver/pgraph_solver_new.exe
Pgraph/solver/pgraph_solver_new2.exe
Pgraph/solver/pgraph_solver_old.exe
Pgraph/solver/test_out - Copy.out
Pgraph/solver/test_out.out
ProcessGraph-1.26.dist-info/LICENSE
ProcessGraph-1.26.dist-info/METADATA
ProcessGraph-1.26.dist-info/WHEEL
ProcessGraph-1.26.dist-info/top_level.txt
ProcessGraph-1.26.dist-info/RECORD
