Metadata-Version: 2.1
Name: ProcessGraph
Version: 1.26
Summary: Connecting Process Network Synthesis (PNS) to Modern Programming Ecosystems
Author: Sin Yong Teng
Author-email: tsyet12@gmail.com
License: BSD 2-Clause
Keywords: Process Optimization,Process Network Synthesis,Artificial Intelligence
Classifier: Development Status :: 4 - Beta
Classifier: Intended Audience :: Developers
Classifier: Topic :: Software Development :: Build Tools
Classifier: License :: OSI Approved :: BSD License
Classifier: Programming Language :: Python :: 3
Classifier: Programming Language :: Python :: 3.4
Classifier: Programming Language :: Python :: 3.5
Classifier: Programming Language :: Python :: 3.6
License-File: LICENSE
Requires-Dist: pydot
Requires-Dist: graphviz
Requires-Dist: matplotlib
Requires-Dist: networkx (>=2.5.0)
Requires-Dist: lxml
